anyads/__init__.py
anyads/client.py
anyads/exceptions.py
anyads/post.py
anyads/task.py
anyads/integrations/__init__.py
anyads/integrations/aiogram_handlers.py
anyads/integrations/aiogram_ui.py
anyads-1.1.8.dist-info/METADATA
anyads-1.1.8.dist-info/WHEEL
anyads-1.1.8.dist-info/RECORD
