Metadata-Version: 2.4
Name: anyads
Version: 1.1.8
Summary: Official SDK for the AnyAds advertising platform for Telegram bots.
Project-URL: Homepage, https://anyads.online
Project-URL: Documentation, https://wiki.anyads.online
Author: MaoMedia AnyAds
Classifier: Framework :: AsyncIO
Classifier: Intended Audience :: Developers
Classifier: License :: OSI Approved :: MIT License
Classifier: Operating System :: OS Independent
Classifier: Programming Language :: Python :: 3
Requires-Python: >=3.8
Requires-Dist: getmac>=0.9.0
Requires-Dist: httpx[http2]>=0.25.0
Provides-Extra: aiogram
Requires-Dist: aiogram>=3.0.0; extra == 'aiogram'
